iviopy.cpython-310-x86_64-linux-gnu.so
iviopy-0.2.0.dist-info/WHEEL
iviopy-0.2.0.dist-info/top_level.txt
iviopy-0.2.0.dist-info/RECORD
iviopy-0.2.0.dist-info/METADATA
