Metadata-Version: 2.1
Name: iviopy
Version: 0.2.0
Summary: IVio bioinformatic file format reader/writer
Author-email: Simon Gene Gottlieb <ivio.simon@gottliebtfreitag.de>
Project-URL: Homepage, https://github.com/SGSSGene/IVio
Classifier: Development Status :: 4 - Beta
Classifier: Operating System :: POSIX :: Linux
Classifier: Natural Language :: English
Classifier: Topic :: Scientific/Engineering :: Bio-Informatics
Requires-Python: >=3.7
